molly/__init__.py
molly/cli.py
molly/constants.py
molly/exceptions.py
molly/molly.py
molly/utils.py
molly/tests/__init__.py
molly/tests/conftest.py
molly/tests/test_cli.py
molly/tests/test_helpers.py
molly/tests/test_molly.py
molly_py-0.1.0.dist-info/METADATA
molly_py-0.1.0.dist-info/WHEEL
molly_py-0.1.0.dist-info/entry_points.txt
molly_py-0.1.0.dist-info/top_level.txt
molly_py-0.1.0.dist-info/RECORD
