Metadata-Version: 2.1
Name: molly-py
Version: 0.1.0
Summary: A multithreaded TCP port scanner.
Home-page: https://github.com/Zabanaa/molly
Author: Karim C
Author-email: karim.cheurfi@gmail.com
License: UNKNOWN
Keywords: multithreaded tcp port scanner
Platform: UNKNOWN
Classifier: Development Status :: 5 - Production/Stable
Classifier: Programming Language :: Python :: 3.7
Classifier: Intended Audience :: Developers
Classifier: Operating System :: OS Independent
Classifier: Topic :: Security
Requires-Python: >=3.7
Requires-Dist: click
